pathfinder/__init__.py
pathfinder/navmesh/__init__.py
pathfinder/navmesh/navmesh_bvh.py
pathfinder/navmesh/navmesh_graph.py
pathfinder/navmesh/navmesh_node.py
pathfinder/navmesh/navmesh_triangle.py
pathfinder/navmesh_baker/__init__.py
pathfinder/navmesh_baker/rc_area.py
pathfinder/navmesh_baker/rc_calcs.py
pathfinder/navmesh_baker/rc_classes.py
pathfinder/navmesh_baker/rc_constants.py
pathfinder/navmesh_baker/rc_contour.py
pathfinder/navmesh_baker/rc_filtering.py
pathfinder/navmesh_baker/rc_heightfield.py
pathfinder/navmesh_baker/rc_mesh.py
pathfinder/navmesh_baker/rc_rasterization.py
pathfinder/pyrvo/__init__.py
pathfinder/pyrvo/agent.py
pathfinder/pyrvo/kd_tree.py
pathfinder/pyrvo/obstacle.py
pathfinder/pyrvo/rvo_simulator.py
pathfinder/pyrvo/utilities.py
pynavmesh-1.2.5.dist-info/LICENSE
pynavmesh-1.2.5.dist-info/METADATA
pynavmesh-1.2.5.dist-info/WHEEL
pynavmesh-1.2.5.dist-info/top_level.txt
pynavmesh-1.2.5.dist-info/RECORD
