Metadata-Version: 2.1
Name: pynavmesh
Version: 1.2.5
Summary: Python implementation of path finding algorithm in navigation meshes
Home-page: https://github.com/Tugcga/Path-Finder
Author: Shekn Itrch
Author-email: cgproggame@gmail.com
Project-URL: Bug Tracker, https://github.com/Tugcga/Path-Finder/issues
Classifier: Programming Language :: Python :: 3
Classifier: License :: OSI Approved :: MIT License
Classifier: Operating System :: OS Independent
Requires-Python: >=3.6
License-File: LICENSE
